dscalculator/README.md
dscalculator/__init__.py
dscalculator/calculator.py
dscalculator/test_calculator.py
dscalculator-1.0.0.dist-info/LICENSE
dscalculator-1.0.0.dist-info/WHEEL
dscalculator-1.0.0.dist-info/METADATA
dscalculator-1.0.0.dist-info/RECORD
