Metadata-Version: 2.1
Name: dscalculator
Version: 1.0.0
Summary: A basic calculator package.
Author-email: Julija Ba <bg.julija@gmail.com>
Classifier: License :: OSI Approved :: MIT License
Project-URL: Home, https://github.com/TuringCollegeSubmissions/jbagin-DWWP.1.5
